sf_helper/__init__.py
sf_helper/cli.py
sf_helper/utils.py
sf_helper-0.0.2.dist-info/entry_points.txt
sf_helper-0.0.2.dist-info/METADATA
sf_helper-0.0.2.dist-info/WHEEL
sf_helper-0.0.2.dist-info/RECORD
