Metadata-Version: 2.3
Name: sf_helper
Version: 0.0.2
Summary: A sample CLI project build with Poetry.
Author: Ian Fogelman
Author-email: IanFogelman@gmail.com
Requires-Python: >=3.8,<4.0
Classifier: Programming Language :: Python :: 3
Classifier: Programming Language :: Python :: 3.8
Classifier: Programming Language :: Python :: 3.9
Classifier: Programming Language :: Python :: 3.10
Classifier: Programming Language :: Python :: 3.11
Classifier: Programming Language :: Python :: 3.12
Classifier: Programming Language :: Python :: 3.13
Requires-Dist: click (>=8.1.3,<9.0.0)
Requires-Dist: requests (>=2.32.3,<3.0.0)
